arxiv_astro_summarizer/__init__.py
arxiv_astro_summarizer/astroph_summarizer.py
arxiv_astro_summarizer-1.3.dist-info/LICENSE.txt
arxiv_astro_summarizer-1.3.dist-info/METADATA
arxiv_astro_summarizer-1.3.dist-info/WHEEL
arxiv_astro_summarizer-1.3.dist-info/top_level.txt
arxiv_astro_summarizer-1.3.dist-info/RECORD
