Metadata-Version: 2.1
Name: arxiv-astro-summarizer
Version: 1.3
Summary: Scrapes arXiv astro-ph paper, summarizes the abstract, and returns relavant papers according to a user input.
Home-page: https://github.com/Professor-G/arxiv-astro-summarizer
Author: Daniel Godines
Author-email: danielgodinez123@gmail.com
License: GPL-3.0
Classifier: Development Status :: 5 - Production/Stable
Classifier: Intended Audience :: Developers
Classifier: Topic :: Software Development :: Build Tools
Classifier: License :: OSI Approved :: GNU General Public License v3 (GPLv3)
Classifier: Programming Language :: Python :: 3
Requires-Python: >=3.7,<4
License-File: LICENSE.txt
Requires-Dist: numpy
Requires-Dist: requests
Requires-Dist: arxivscraper
Requires-Dist: pandas
Requires-Dist: PyPDF2
Requires-Dist: transformers
Requires-Dist: scikit-learn
Requires-Dist: nltk
Requires-Dist: datefinder
Requires-Dist: tensorflow
Requires-Dist: torch
Requires-Dist: progress
Requires-Dist: pdfplumber
